nexus_client_sdk/.extensions/cext_version
nexus_client_sdk/.extensions/nexus_sdk.so
nexus_client_sdk/__init__.py
nexus_client_sdk/_version.py
nexus_client_sdk/clients/__init__.py
nexus_client_sdk/clients/cwrapper.py
nexus_client_sdk/clients/fault_tolerance/__init__.py
nexus_client_sdk/clients/fault_tolerance/models/__init__.py
nexus_client_sdk/clients/fault_tolerance/models/_models.py
nexus_client_sdk/clients/fault_tolerance/retry_policy.py
nexus_client_sdk/clients/fault_tolerance/sync_retry_policy.py
nexus_client_sdk/clients/nexus_receiver_client.py
nexus_client_sdk/clients/nexus_scheduler_client.py
nexus_client_sdk/clients/sync_helpers/__init__.py
nexus_client_sdk/clients/sync_helpers/_functions.py
nexus_client_sdk/models/__init__.py
nexus_client_sdk/models/access_token.py
nexus_client_sdk/models/client_errors/__init__.py
nexus_client_sdk/models/client_errors/go_http_errors.py
nexus_client_sdk/models/common.py
nexus_client_sdk/models/receiver.py
nexus_client_sdk/models/scheduler.py
nexus_client_sdk/nexus/__init__.py
nexus_client_sdk/nexus/abstractions/__init__.py
nexus_client_sdk/nexus/abstractions/algorithm_cache.py
nexus_client_sdk/nexus/abstractions/input_object.py
nexus_client_sdk/nexus/abstractions/logger_factory.py
nexus_client_sdk/nexus/abstractions/metrics_provider_factory.py
nexus_client_sdk/nexus/abstractions/nexus_object.py
nexus_client_sdk/nexus/abstractions/socket_provider.py
nexus_client_sdk/nexus/algorithms/__init__.py
nexus_client_sdk/nexus/algorithms/_baseline_algorithm.py
nexus_client_sdk/nexus/algorithms/_remote_algorithm.py
nexus_client_sdk/nexus/algorithms/distributed.py
nexus_client_sdk/nexus/algorithms/forked_algorithm.py
nexus_client_sdk/nexus/algorithms/minimalistic.py
nexus_client_sdk/nexus/algorithms/recursive.py
nexus_client_sdk/nexus/async_extensions/__init__.py
nexus_client_sdk/nexus/async_extensions/async_exec/__init__.py
nexus_client_sdk/nexus/async_extensions/async_exec/_functions.py
nexus_client_sdk-1.3.8.dist-info/METADATA
nexus_client_sdk-1.3.8.dist-info/WHEEL
nexus_client_sdk-1.3.8.dist-info/licenses/LICENSE
nexus_client_sdk-1.3.8.dist-info/RECORD
