Metadata-Version: 2.4
Name: nexus-client-sdk
Version: 1.3.8
Summary: Nexus SDK library for Python.
License: Apache-2.0
License-File: LICENSE
Author: ECCO Sneaks & Data
Author-email: esdsupport@ecco.com
Maintainer: ECCO Sneaks & Data
Maintainer-email: esdsupport@ecco.com
Requires-Python: >=3.11,<3.13
Classifier: License :: OSI Approved :: Apache Software License
Classifier: Programming Language :: Python :: 3
Classifier: Programming Language :: Python :: 3.11
Classifier: Programming Language :: Python :: 3.12
Requires-Dist: adapta[aws,datadog,storage] (>=3.5.7,<4.0.0)
Requires-Dist: injector (>=0.22.0,<0.23.0)
Project-URL: Repository, https://github.com/SneaksAndData/nexus-sdk-py
